src/__init__.py
src/SEED_Attacks/__init__.py
src/SEED_Attacks/attacker.py
src/SEED_Attacks/SEED_Poisoning/__init__.py
src/SEED_Attacks/SEED_Poisoning/utils/__init__.py
src/SEED_Attacks/SEED_Poisoning/utils/seed_poison_attack.py
src/SEED_Attacks/SEED_Poisoning/utils/trigger_generation.py
src/SEED_Attacks/evaluation/__init__.py
src/SEED_Attacks/evaluation/mrr_evaluation.py
src/core/__init__.py
src/core/config.py
seedpoisoner-0.0.1.dist-info/LICENSE
seedpoisoner-0.0.1.dist-info/METADATA
seedpoisoner-0.0.1.dist-info/WHEEL
seedpoisoner-0.0.1.dist-info/top_level.txt
seedpoisoner-0.0.1.dist-info/RECORD
